Metadata-Version: 1.0
Name: httpfingerprint
Version: 0.1
Summary: No description at this moment
Home-page: https://github.com/try3xcept/httpfingerprint
Author: try3xcept
Author-email: try3xcept@gmail.com
License: MIT
Platform: UNKNOWN
